dynamic_drf/__init__.py
dynamic_drf/apps.py
dynamic_drf/auth.py
dynamic_drf/dyn_settings.py
dynamic_drf/models.py
dynamic_drf/serializers.py
dynamic_drf/views.py
dynamic_drf-0.2.dist-info/METADATA
dynamic_drf-0.2.dist-info/WHEEL
dynamic_drf-0.2.dist-info/top_level.txt
dynamic_drf-0.2.dist-info/RECORD
