Metadata-Version: 2.1
Name: dynamic_drf
Version: 0.2
Summary: A package that overrides the default drf spectacular
Author: Atit Sharma
Requires-Dist: Django ==5.0.4
Requires-Dist: drf-spectacular ==0.27.2
Requires-Dist: djangorestframework ==3.15.1
